plsma/__init__.py
plsma/cli.py
plsma/utils.py
plsma/commands/__init__.py
plsma/commands/base.py
plsma/commands/help.py
plsma/commands/registry.py
plsma/commands/file/__init__.py
plsma/commands/file/backup.py
plsma/commands/file/size.py
plsma/commands/git/__init__.py
plsma/commands/git/status.py
plsma/commands/git/sync.py
plsma/commands/git/undo.py
plsma/commands/ip/__init__.py
plsma/commands/ip/list.py
plsma/commands/ip/ping.py
plsma/commands/ip/port.py
plsma/commands/ip/subnet.py
plsma/commands/ip/validate.py
plsma/commands/project/__init__.py
plsma/commands/project/license.py
plsma/commands/project/licenses/__init__.py
plsma/commands/project/licenses/apache.py
plsma/commands/project/licenses/gpl.py
plsma/commands/project/licenses/mit.py
plsma/commands/project/licenses/unlicense.py
plsma/commands/server/__init__.py
plsma/commands/server/find.py
plsma/commands/server/kill.py
plsma/commands/server/ports.py
plsma-0.1.1.dist-info/METADATA
plsma-0.1.1.dist-info/WHEEL
plsma-0.1.1.dist-info/entry_points.txt
plsma-0.1.1.dist-info/licenses/LICENSE
plsma-0.1.1.dist-info/RECORD
