Metadata-Version: 2.4
Name: plsma
Version: 0.1.1
Summary: A developer's toolkit for managing and automating development tasks.
License-File: LICENSE
Requires-Python: >=3.10
Requires-Dist: click>=8.2.1
Requires-Dist: psutil>=7.0.0
Requires-Dist: rich>=14.0.0
